pytest_modern/__init__.py
pytest_modern/benchmark_report.py
pytest_modern/coverage_report.py
pytest_modern/header.py
pytest_modern/plugin.py
pytest_modern/terminal.py
pytest_modern/traceback.py
pytest_modern-0.7.4.dist-info/METADATA
pytest_modern-0.7.4.dist-info/WHEEL
pytest_modern-0.7.4.dist-info/entry_points.txt
pytest_modern-0.7.4.dist-info/licenses/LICENSE
pytest_modern-0.7.4.dist-info/RECORD
