Metadata-Version: 2.4
Name: pytest-modern
Version: 0.7.4
Summary: A more modern pytest
Author-email: "ZhengYu, Xu" <zen-xu@outlook.com>
License-File: LICENSE
Classifier: Development Status :: 4 - Beta
Classifier: Framework :: Pytest
Classifier: Intended Audience :: Developers
Classifier: License :: OSI Approved :: Apache Software License
Classifier: Operating System :: MacOS
Classifier: Operating System :: Microsoft :: Windows
Classifier: Operating System :: POSIX
Classifier: Operating System :: Unix
Classifier: Programming Language :: Python :: 3 :: Only
Classifier: Programming Language :: Python :: 3.9
Classifier: Programming Language :: Python :: 3.10
Classifier: Programming Language :: Python :: 3.11
Classifier: Programming Language :: Python :: 3.12
Classifier: Programming Language :: Python :: 3.13
Classifier: Programming Language :: Python :: 3.14
Classifier: Topic :: Software Development :: Libraries
Classifier: Topic :: Software Development :: Testing
Classifier: Topic :: Utilities
Requires-Python: <4,>=3.9
Requires-Dist: pytest>=8
Requires-Dist: rich>=10
Provides-Extra: benchmark
Requires-Dist: pytest-benchmark>=5; extra == 'benchmark'
Provides-Extra: coverage
Requires-Dist: pytest-cov>=6; extra == 'coverage'
Provides-Extra: rerun
Requires-Dist: pytest-rerunfailures>=15; extra == 'rerun'
Provides-Extra: timeout
Requires-Dist: pytest-timeout>=2; extra == 'timeout'
